pynll/__init__.py
pynll/grid.py
pynll/nlloc/CHANGE_NOTES.txt
pynll/nlloc/Grid2GMT.c
pynll/nlloc/Grid2Time1.c
pynll/nlloc/GridCascadingDecimate.c
pynll/nlloc/GridGraphLib.c
pynll/nlloc/GridGraphLib.h
pynll/nlloc/GridLib.c
pynll/nlloc/GridLib.h
pynll/nlloc/GridMemLib.c
pynll/nlloc/GridMemLib.h
pynll/nlloc/Loc2ddct.c
pynll/nlloc/LocSum.c
pynll/nlloc/Makefile
pynll/nlloc/NLDiffLoc.c
pynll/nlloc/NLLoc1.c
pynll/nlloc/NLLocLib.c
pynll/nlloc/NLLocLib.h
pynll/nlloc/NLLoc_func_test.c
pynll/nlloc/NLLoc_main.c
pynll/nlloc/PhsAssoc
pynll/nlloc/PhsAssoc.c
pynll/nlloc/README.txt
pynll/nlloc/Time2Angles1.c
pynll/nlloc/Time2EQ
pynll/nlloc/Time2EQ1.c
pynll/nlloc/Time_3d_NLL.c
pynll/nlloc/Vel2Grid1.c
pynll/nlloc/Vel2Grid3D.c
pynll/nlloc/__init__.py
pynll/nlloc/alomax_matrix/alomax_matrix.c
pynll/nlloc/alomax_matrix/alomax_matrix.h
pynll/nlloc/alomax_matrix/alomax_matrix_svd.c
pynll/nlloc/alomax_matrix/alomax_matrix_svd.h
pynll/nlloc/alomax_matrix/eigv.c
pynll/nlloc/alomax_matrix/eigv.h
pynll/nlloc/alomax_matrix/polarization.c
pynll/nlloc/alomax_matrix/polarization.h
pynll/nlloc/alomax_matrix/test_real_symmetric_eigen.c
pynll/nlloc/calc_crust_corr.c
pynll/nlloc/calc_crust_corr.h
pynll/nlloc/crust_corr_model.h
pynll/nlloc/crust_type.h
pynll/nlloc/crust_type_key.h
pynll/nlloc/fmm2grid
pynll/nlloc/fmm2grid.c
pynll/nlloc/fpfit2hyp.c
pynll/nlloc/geo.c
pynll/nlloc/geo.h
pynll/nlloc/geometry/geometry.h
pynll/nlloc/hypoe2hyp.c
pynll/nlloc/interface2fmm.c
pynll/nlloc/loclist.c
pynll/nlloc/mag_func_test.c
pynll/nlloc/map_project.c
pynll/nlloc/map_project.h
pynll/nlloc/matrix_statistics/matrix_statistics.c
pynll/nlloc/matrix_statistics/matrix_statistics.h
pynll/nlloc/matrix_statistics/matrix_statistics_DEV.c
pynll/nlloc/matrix_statistics/matrix_statistics_DEV.h
pynll/nlloc/matrix_statistics/test_ellipsoid.c
pynll/nlloc/oct2grid.c
pynll/nlloc/octtree/geometry.h
pynll/nlloc/octtree/octtree.c
pynll/nlloc/octtree/octtree.h
pynll/nlloc/octtree/ran1.h
pynll/nlloc/otime_limit.c
pynll-0.1.0.dist-info/entry_points.txt
pynll-0.1.0.dist-info/LICENSE
pynll-0.1.0.dist-info/WHEEL
pynll-0.1.0.dist-info/METADATA
pynll-0.1.0.dist-info/RECORD
