Metadata-Version: 2.1
Name: pynll
Version: 0.1.0
Summary: wrapper around A. Lomax NLLoc
Author: jpmercier
Author-email: jpmercier01@gmail.com
Requires-Python: >=3.8,<4.0
Classifier: Programming Language :: Python :: 3
Classifier: Programming Language :: Python :: 3.8
Requires-Dist: setuptools_cpp (>=0.1.0,<0.2.0)
Requires-Dist: uquake (>=0.1.0,<0.2.0)
